snowdrop_tangled_game_engine/__init__.py
snowdrop_tangled_game_engine/base_agent.py
snowdrop_tangled_game_engine/base_game_player.py
snowdrop_tangled_game_engine/game.py
snowdrop_tangled_game_engine/game_graph_ground_truth.py
snowdrop_tangled_game_engine/game_types.py
snowdrop_tangled_game_engine/local_game_player.py
snowdrop_tangled_game_engine-1.1.0.dist-info/licenses/LICENSE
snowdrop_tangled_game_engine-1.1.0.dist-info/METADATA
snowdrop_tangled_game_engine-1.1.0.dist-info/WHEEL
snowdrop_tangled_game_engine-1.1.0.dist-info/RECORD
