Metadata-Version: 2.4
Name: snowdrop-tangled-game-engine
Version: 1.1.0
Summary: A package for the Tangled game engine and support classes.
License: MIT
License-File: LICENSE
Author: Geordie Rose
Author-email: greatblueheron@users.noreply.github.com
Requires-Python: >=3.11,<3.14
Classifier: License :: OSI Approved :: MIT License
Classifier: Programming Language :: Python :: 3
Classifier: Programming Language :: Python :: 3.11
Classifier: Programming Language :: Python :: 3.12
Classifier: Programming Language :: Python :: 3.13
Requires-Dist: pydantic (>=2.0.0)
Requires-Dist: python-dateutil (>=2.5.3)
Requires-Dist: requests (>=2.31.0)
Requires-Dist: typing-extensions (>=4.7.1)
Requires-Dist: urllib3 (>=2.5.0)
Project-URL: Bug Tracker, https://github.com/snowdropquantum/snowdrop-tangled-game-package/issues
Project-URL: Documentation, https://github.com/snowdropquantum/snowdrop-tangled-game-package
Project-URL: Homepage, https://github.com/snowdropquantum/snowdrop-tangled-game-package
Project-URL: Repository, https://github.com/snowdropquantum/snowdrop-tangled-game-package
